FrozenDesert-0.1a1.dist-info/METADATA
FrozenDesert-0.1a1.dist-info/RECORD
FrozenDesert-0.1a1.dist-info/WHEEL
FrozenDesert-0.1a1.dist-info/top_level.txt
main/__init__.py
main/bootUp.py
main/userIdentification.py
main/utils.py
