Metadata-Version: 2.1
Name: FrozenDesert
Version: 0.1a1
Summary: Frozen Desert is a small Text-Adventure With 10 classes & 3 storylines, allowing for much variety.
Home-page: UNKNOWN
Author: Zachary // 2VeryIcey
Author-email: 2veryicey@gmail.com
License: UNKNOWN
Keywords: game text adventure fun small simple story storyline frozen desert oregon trail kingdom loathing
Platform: UNKNOWN
